{
	"info": {
		"_postman_id": "cdaa4905-6e7e-444b-95dc-fe75f5f090c0",
		"name": "Creating Simple API",
		"schema": "https://schema.getpostman.com/json/collection/v2.1.0/collection.json"
	},
	"item": [
		{
			"name": "user",
			"item": [
				{
					"name": "register",
					"request": {
						"method": "POST",
						"header": [],
						"body": {
							"mode": "raw",
							"raw": "{\r\n    \"name\": \"andi\",\r\n    \"email\": \"andi@example.com\",\r\n    \"password\": \"123456\"\r\n}",
							"options": {
								"raw": {
									"language": "json"
								}
							}
						},
						"url": {
							"raw": "{{BASE_URL}}/user/register",
							"host": [
								"{{BASE_URL}}"
							],
							"path": [
								"user",
								"register"
							]
						}
					},
					"response": []
				},
				{
					"name": "login",
					"request": {
						"method": "POST",
						"header": [],
						"body": {
							"mode": "raw",
							"raw": "{\r\n    \"email\": \"andi@example.com\",\r\n    \"password\": \"123456\"\r\n}",
							"options": {
								"raw": {
									"language": "json"
								}
							}
						},
						"url": {
							"raw": "{{BASE_URL}}/user/login",
							"host": [
								"{{BASE_URL}}"
							],
							"path": [
								"user",
								"login"
							]
						}
					},
					"response": []
				}
			],
			"protocolProfileBehavior": {}
		},
		{
			"name": "question",
			"item": [
				{
					"name": "add question",
					"request": {
						"auth": {
							"type": "bearer",
							"bearer": [
								{
									"key": "token",
									"value": "",
									"type": "string"
								}
							]
						},
						"method": "POST",
						"header": [],
						"body": {
							"mode": "raw",
							"raw": "{\r\n    \"question\": \"lorem ipsum dolor sit amet consectetur adipiscing elit\"\r\n}",
							"options": {
								"raw": {
									"language": "json"
								}
							}
						},
						"url": {
							"raw": "{{BASE_URL}}/question",
							"host": [
								"{{BASE_URL}}"
							],
							"path": [
								"question"
							]
						}
					},
					"response": []
				},
				{
					"name": "get all question",
					"request": {
						"auth": {
							"type": "bearer",
							"bearer": [
								{
									"key": "token",
									"value": "",
									"type": "string"
								}
							]
						},
						"method": "GET",
						"header": [],
						"url": {
							"raw": "{{BASE_URL}}/question?page=1&limit=20",
							"host": [
								"{{BASE_URL}}"
							],
							"path": [
								"question"
							],
							"query": [
								{
									"key": "page",
									"value": "1"
								},
								{
									"key": "limit",
									"value": "20"
								}
							]
						}
					},
					"response": []
				},
				{
					"name": "get question",
					"request": {
						"auth": {
							"type": "bearer",
							"bearer": [
								{
									"key": "token",
									"value": "",
									"type": "string"
								}
							]
						},
						"method": "GET",
						"header": [],
						"url": {
							"raw": "{{BASE_URL}}/question/{{UUID}}",
							"host": [
								"{{BASE_URL}}"
							],
							"path": [
								"question",
								"{{UUID}}"
							]
						}
					},
					"response": []
				},
				{
					"name": "update question",
					"request": {
						"auth": {
							"type": "bearer",
							"bearer": [
								{
									"key": "token",
									"value": "",
									"type": "string"
								}
							]
						},
						"method": "PUT",
						"header": [],
						"body": {
							"mode": "raw",
							"raw": "{\r\n    \"question\": \"update lorem ipsum dolor sit amet consectetur adipiscing elit\",\r\n    \"is_active\": true\r\n}",
							"options": {
								"raw": {
									"language": "json"
								}
							}
						},
						"url": {
							"raw": "{{BASE_URL}}/question/{{UUID}}",
							"host": [
								"{{BASE_URL}}"
							],
							"path": [
								"question",
								"{{UUID}}"
							]
						}
					},
					"response": []
				},
				{
					"name": "delete question",
					"request": {
						"auth": {
							"type": "bearer",
							"bearer": [
								{
									"key": "token",
									"value": "",
									"type": "string"
								}
							]
						},
						"method": "DELETE",
						"header": [],
						"url": {
							"raw": "{{BASE_URL}}/question/{{UUID}}",
							"host": [
								"{{BASE_URL}}"
							],
							"path": [
								"question",
								"{{UUID}}"
							]
						}
					},
					"response": []
				}
			],
			"protocolProfileBehavior": {}
		}
	],
	"protocolProfileBehavior": {}
}